setup.py
dm/__init__.py
dm.historical.egg-info/PKG-INFO
dm.historical.egg-info/SOURCES.txt
dm.historical.egg-info/dependency_links.txt
dm.historical.egg-info/namespace_packages.txt
dm.historical.egg-info/top_level.txt
dm.historical.egg-info/zip-safe
dm/historical/CHANGES.txt
dm/historical/LICENSE.txt
dm/historical/README.txt
dm/historical/VERSION.txt
dm/historical/__init__.py
dm/historical/connection.py