Metadata-Version: 1.1
Name: dm.historical
Version: 1.2
Summary: Historical state of objects stored in the ZODB
Home-page: UNKNOWN
Author: Dieter Maurer
Author-email: dieter@handshake.de
License: BSD (see "dm/historical/LICENSE.txt", for details)
Keywords: historical state ZODB analysis recovery
Platform: UNKNOWN
Classifier: Development Status :: 5 - Production/Stable
Classifier: Framework :: ZODB
Classifier: Intended Audience :: Developers
Classifier: Intended Audience :: System Administrators
Classifier: License :: OSI Approved :: BSD License
Classifier: Operating System :: OS Independent
Classifier: Programming Language :: Python
Classifier: Topic :: Database
Classifier: Topic :: Utilities
